<layouts>
   <layout name="root">
      <row>
         <button type="tag" label="parada no marcadas" icon="/bus_route_icons/Junglebus-04.png" />
         <button type="tag" label="barra de parada" icon="/bus_route_icons/Junglebus-05.png" />
         <button type="tag" label="parada cubierta" icon="/bus_route_icons/Junglebus-06.png" />
      </row>
      <row></row>
      <row></row>
      <row>
         <button type="textnote" label="Text note" icon="text.png" />
      </row>
      <row></row>
      <row></row>

   </layout>
</layouts>